PostMeshPy.so
PostMeshPy-1.6.1.dist-info/METADATA
PostMeshPy-1.6.1.dist-info/RECORD
PostMeshPy-1.6.1.dist-info/WHEEL
PostMeshPy-1.6.1.dist-info/top_level.txt
