Metadata-Version: 2.1
Name: PostMeshPy
Version: 1.6.1
Summary: A Python wrapper for PostMesh - a high order curvilinear mesh generator based on OpenCascade
Home-page: https://github.com/romeric/PostMesh
Author: Roman Poya
Author-email: roman_poya@yahoo.com
License: MIT
Platform: UNKNOWN
Requires-Dist: numpy (>=1.9)
Requires-Dist: cython (>=0.23)
